dragon_baseline/__init__.py
dragon_baseline/__main__.py
dragon_baseline/main.py
dragon_baseline/nlp_algorithm.py
dragon_baseline/run_classification.py
dragon_baseline/run_classification_multi_label.py
dragon_baseline/run_ner.py
dragon_baseline/architectures/__init__.py
dragon_baseline/architectures/clf_multi_head.py
dragon_baseline/architectures/ner_multi_head.py
dragon_baseline/architectures/reg_multi_head.py
dragon_baseline-0.4.6.dist-info/licenses/LICENSE
dragon_baseline-0.4.6.dist-info/METADATA
dragon_baseline-0.4.6.dist-info/WHEEL
dragon_baseline-0.4.6.dist-info/top_level.txt
dragon_baseline-0.4.6.dist-info/RECORD
