Metadata-Version: 2.4
Name: dragon_baseline
Version: 0.4.6
Summary: Baseline training algorithm for the DRAGON Challenge
Home-page: https://github.com/DIAGNijmegen/dragon_baseline
Author: Joeran Bosma
Author-email: Joeran.Bosma@radboudumc.nl
Project-URL: Bug Tracker, https://github.com/DIAGNijmegen/dragon_baseline/issues
Platform: unix
Platform: linux
Platform: osx
Platform: cygwin
Platform: win32
Classifier: Programming Language :: Python :: 3
Classifier: Programming Language :: Python :: 3 :: Only
Classifier: Programming Language :: Python :: 3.9
Classifier: Programming Language :: Python :: 3.10
Classifier: Programming Language :: Python :: 3.11
Classifier: Programming Language :: Python :: 3.12
Classifier: Programming Language :: Python :: 3.13
Requires-Python: >=3.9
License-File: LICENSE
Requires-Dist: torch
Requires-Dist: transformers>=4.48.0
Requires-Dist: datasets
Requires-Dist: evaluate
Requires-Dist: accelerate
Requires-Dist: xformers
Requires-Dist: pandas
Requires-Dist: seqeval
Requires-Dist: scikit-learn==1.5.2
Provides-Extra: testing
Requires-Dist: pytest>=6.0; extra == "testing"
Requires-Dist: pytest-cov>=2.0; extra == "testing"
Requires-Dist: mypy>=0.910; extra == "testing"
Requires-Dist: flake8>=3.9; extra == "testing"
Requires-Dist: tox>=3.24; extra == "testing"
Dynamic: author-email
Dynamic: description
Dynamic: description-content-type
Dynamic: home-page
Dynamic: license-file
Dynamic: project-url
